createsonline/__init__.py
createsonline/app.py
createsonline/database.py
createsonline/database_session.py
createsonline/decorators.py
createsonline/editor.py
createsonline/middleware.py
createsonline/project_init.py
createsonline/routing.py
createsonline/seo.py
createsonline/seo_middleware.py
createsonline/server.py
createsonline/session.py
createsonline/static_files.py
createsonline/templates.py
createsonline/testing.py
createsonline/upload_handler.py
createsonline/utils.py
createsonline/views.py
createsonline/admin/__init__.py
createsonline/admin/content.py
createsonline/admin/crud.py
createsonline/admin/field_builder.py
createsonline/admin/integration.py
createsonline/admin/interface.py
createsonline/admin/model_creator.py
createsonline/admin/model_manager.py
createsonline/admin/modern_dashboard.py
createsonline/admin/permissions.py
createsonline/admin/user_forms.py
createsonline/ai/__init__.py
createsonline/ai/fields.py
createsonline/ai/orm.py
createsonline/ai/services.py
createsonline/auth/__init__.py
createsonline/auth/management.py
createsonline/auth/models.py
createsonline/cli/__init__.py
createsonline/cli/main.py
createsonline/cli/manage.py
createsonline/cli/commands/__init__.py
createsonline/cli/commands/database.py
createsonline/cli/commands/info.py
createsonline/cli/commands/initdb.py
createsonline/cli/commands/project.py
createsonline/cli/commands/serve.py
createsonline/cli/commands/shell.py
createsonline/cli/commands/users.py
createsonline/config/__init__.py
createsonline/config/app.py
createsonline/config/database.py
createsonline/config/docs.py
createsonline/config/errors.py
createsonline/config/orm.py
createsonline/config/request.py
createsonline/config/settings.py
createsonline/data/__init__.py
createsonline/data/dataframe.py
createsonline/data/excel.py
createsonline/data/excel_writer.py
createsonline/data/io.py
createsonline/data/series.py
createsonline/database/__init__.py
createsonline/database/abstraction.py
createsonline-0.1.69.dist-info/licenses/LICENSE
createsonline-0.1.69.dist-info/METADATA
createsonline-0.1.69.dist-info/WHEEL
createsonline-0.1.69.dist-info/entry_points.txt
createsonline-0.1.69.dist-info/top_level.txt
createsonline-0.1.69.dist-info/RECORD
